nonebot_plugin_jmcomicdownload/__init__.py
nonebot_plugin_jmcomicdownload/config.yml
nonebot_plugin_jmcomicdownload-1.1.6.dist-info/METADATA
nonebot_plugin_jmcomicdownload-1.1.6.dist-info/WHEEL
nonebot_plugin_jmcomicdownload-1.1.6.dist-info/licenses/LICENSE
nonebot_plugin_jmcomicdownload-1.1.6.dist-info/RECORD
