Metadata-Version: 2.4
Name: nonebot_plugin_jmcomicdownload
Version: 1.1.6
Summary: A NoneBot2 plugin to download comics from JMComic and generate PDFs for upload to group chats.
Project-URL: Homepage, https://github.com/watshon14/nonebot_plugin_jmcomicdownload
Project-URL: Repository, https://github.com/watshon14/nonebot_plugin_jmcomicdownload.git
Author-email: watshon14 <2128433395@qq.com>
License-Expression: MIT
License-File: LICENSE
Keywords: jmcomic,nonebot2,plugin
Requires-Python: <4.0,>=3.9
Requires-Dist: img2pdf>=0.6.0
Requires-Dist: jmcomic>=2.5.32
Requires-Dist: nonebot-adapter-onebot>=2.3
Requires-Dist: nonebot-plugin-localstore>=0.7
Requires-Dist: nonebot2>=2.4.0
